log_api/__init__.py
log_api/admin.py
log_api/apps.py
log_api/models.py
log_api/settings.py
log_api/tests.py
log_api/urls.py
log_api/views.py
django_log_api-0.1.3.dist-info/LICENSE
django_log_api-0.1.3.dist-info/WHEEL
django_log_api-0.1.3.dist-info/METADATA
django_log_api-0.1.3.dist-info/RECORD
