Metadata-Version: 2.1
Name: django-log-api
Version: 0.1.3
Summary: Allows download django log file via api
Home-page: https://pypi.org/project/django-log-api
License: MIT
Keywords: django,log,djangorestframework
Author: luocy
Author-email: luocy77@gmail.com
Requires-Python: >=3.6
Classifier: Development Status :: 5 - Production/Stable
Classifier: Environment :: Web Environment
Classifier: Framework :: Django
Classifier: Intended Audience :: Developers
Classifier: License :: OSI Approved :: MIT License
Classifier: Natural Language :: English
Classifier: Operating System :: OS Independent
Classifier: Programming Language :: Python :: 3
Classifier: Programming Language :: Python :: 3.10
Classifier: Programming Language :: Python :: 3.6
Classifier: Programming Language :: Python :: 3.7
Classifier: Programming Language :: Python :: 3.8
Classifier: Programming Language :: Python :: 3.9
Classifier: Topic :: Internet
Classifier: Topic :: Software Development :: Libraries :: Python Modules
Requires-Dist: django (>=2.2)
Requires-Dist: djangorestframework (>=3.9.2)
Requires-Dist: tailhead (>=1.0.2)
Project-URL: Repository, https://github.com/Luocy7/django-log-api
